[
    {
        "username": "Simon",
        "favoriteTeams": [
            1,
            2
        ],
        "favoritePlayers": [
            20000441,
            20000452
        ],
        "headerFooterColor": 4280364313,
        "comingsMatchsColor": 4290010158,
        "latestsMatchsColor": 4280151434,
        "todaysMatchsColor": 4288328374,
        "teamsHeaderColor": 4280364313,
        "teamsStadiumColor": 4290010158,
        "teamsPlayersColor": 4288328374,
        "backgroundColor": 4279303467
    },
    {
        "username": "Quentin",
        "favoriteTeams": [
            3,
            4
        ],
        "favoritePlayers": [
            20000455,
            20000456
        ],
        "headerFooterColor": 4280364313,
        "comingsMatchsColor": 4290010158,
        "latestsMatchsColor": 4280151434,
        "todaysMatchsColor": 4288328374,
        "teamsHeaderColor": 4280364313,
        "teamsStadiumColor": 4290010158,
        "teamsPlayersColor": 4288328374,
        "backgroundColor": 4279303467
    },
    {
        "username": "Ethan",
        "favoriteTeams": [
            5,
            6
        ],
        "favoritePlayers": [
            20000457,
            20000464
        ],
        "headerFooterColor": 4280364313,
        "comingsMatchsColor": 4290010158,
        "latestsMatchsColor": 4280151434,
        "todaysMatchsColor": 4288328374,
        "teamsHeaderColor": 4280364313,
        "teamsStadiumColor": 4290010158,
        "teamsPlayersColor": 4288328374,
        "backgroundColor": 4279303467
    }
]